{
  "file_version": 1,
  "cmdline:": "cyclictest -a 0 -p 99 -m -i 1000 -D300 -h 500 --json=cpubench1M/preempt_rt_xen/cyclic_stress_1cores.json -q",
  "rt_test_version:": "2.60",
  "start_time": "Wed, 28 Feb 2024 16:09:23 +0000",
  "end_time": "Wed, 28 Feb 2024 16:14:24 +0000",
  "return_code": 0,
  "sysinfo": {
    "sysname": "Linux",
    "nodename": "imx95-19x19-lpddr5-evk",
    "release": "6.6.36-rt35-lts-next",
    "version": "#1 SMP PREEMPT_RT Fri Mar 21 00:14:48 UTC 2025",
    "machine": "aarch64",
    "realtime": 1
  },
  "num_threads": 1,
  "resolution_in_ns": 0,
  "thread": {
    "0": {
      "histogram": {
        "10": 15,
        "11": 86,
        "12": 1352,
        "13": 4887,
        "14": 14385,
        "15": 29421,
        "16": 39968,
        "17": 47380,
        "18": 52511,
        "19": 45585,
        "20": 29426,
        "21": 13939,
        "22": 4998,
        "23": 1889,
        "24": 1555,
        "25": 2510,
        "26": 3360,
        "27": 2855,
        "28": 1651,
        "29": 863,
        "30": 513,
        "31": 322,
        "32": 157,
        "33": 105,
        "34": 68,
        "35": 62,
        "36": 42,
        "37": 32,
        "38": 19,
        "39": 6,
        "40": 2,
        "41": 6,
        "42": 4,
        "43": 1,
        "44": 1,
        "45": 1,
        "46": 1,
        "47": 1,
        "48": 3,
        "50": 2,
        "51": 1,
        "53": 1,
        "55": 1,
        "57": 1,
        "58": 1,
        "60": 1,
        "62": 1,
        "63": 1,
        "66": 1,
        "71": 1,
        "74": 1,
        "78": 2,
        "79": 1,
        "81": 1,
        "86": 1
      },
      "cycles": 300000,
      "min": 10,
      "max": 86,
      "avg": 17.98,
      "cpu": 0,
      "node": 0
    }
  }
}
