{
  "file_version": 1,
  "cmdline:": "cyclictest -p 99 -m -i 1000 -D300 -q -a 0 --json=preempt_rt_xen_static/cyclic_stress_mem_1M_3cores_preempt_rt_xen_static.json --histogram=4000 --histfile=preempt_rt_xen_static/cyclic_stress_mem_1M_3cores_preempt_rt_xen_static.hist",
  "rt_test_version:": "2.60",
  "start_time": "Sun, 12 Apr 2026 12:18:12 +0000",
  "end_time": "Sun, 12 Apr 2026 12:23:12 +0000",
  "return_code": 0,
  "sysinfo": {
    "sysname": "Linux",
    "nodename": "amd-edf",
    "release": "6.12.40-xilinx-g31626ef92ff1",
    "version": "#1 SMP PREEMPT_RT Fri Nov  7 15:28:23 UTC 2025",
    "machine": "aarch64",
    "realtime": 0
  },
  "num_threads": 1,
  "resolution_in_ns": 0,
  "thread": {
    "0": {
      "histogram": {
        "19": 5,
        "20": 24,
        "21": 98,
        "22": 231,
        "23": 475,
        "24": 758,
        "25": 1147,
        "26": 1355,
        "27": 1572,
        "28": 1790,
        "29": 2041,
        "30": 2347,
        "31": 2808,
        "32": 3496,
        "33": 4207,
        "34": 5260,
        "35": 7042,
        "36": 10134,
        "37": 15430,
        "38": 22337,
        "39": 28440,
        "40": 31551,
        "41": 31419,
        "42": 28355,
        "43": 22796,
        "44": 16887,
        "45": 12122,
        "46": 8170,
        "47": 5421,
        "48": 3645,
        "49": 2446,
        "50": 1835,
        "51": 1539,
        "52": 1316,
        "53": 1406,
        "54": 1450,
        "55": 1397,
        "56": 1325,
        "57": 1277,
        "58": 1110,
        "59": 1077,
        "60": 1063,
        "61": 1147,
        "62": 1293,
        "63": 1225,
        "64": 1353,
        "65": 1280,
        "66": 1149,
        "67": 969,
        "68": 793,
        "69": 586,
        "70": 460,
        "71": 344,
        "72": 217,
        "73": 176,
        "74": 109,
        "75": 66,
        "76": 63,
        "77": 40,
        "78": 26,
        "79": 19,
        "80": 15,
        "81": 10,
        "82": 11,
        "83": 9,
        "84": 6,
        "85": 2,
        "86": 6,
        "87": 7,
        "88": 1,
        "89": 2,
        "90": 4,
        "91": 3,
        "92": 1,
        "93": 1,
        "95": 1,
        "97": 1,
        "100": 1
      },
      "cycles": 300000,
      "min": 19,
      "max": 100,
      "avg": 41.57,
      "cpu": 0,
      "node": -1
    }
  }
}
